Metadata-Version: 1.2
Name: folder-rotator
Version: 0.0.5
Summary: UNKNOWN
Home-page: https://github.com/kevinglasson/folder_rotator
Author: Kevin Glasson
Author-email: kevinglasson+folderrotator@gmail.com
License: LICENSE.txt
Platform: UNKNOWN
Classifier: Development Status :: 3 - Alpha
Classifier: Intended Audience :: Developers
Classifier: Programming Language :: Python :: 3.6
Requires-Python: >3.6
